clochette/Clochette.py
clochette/__init__.py
clochette/application/__init__.py
clochette/application/i18n/I18nService.py
clochette/application/i18n/LangHelper.py
clochette/application/i18n/LocaleProvider.py
clochette/application/i18n/__init__.py
clochette/application/repository/CalendarAuthenticationRepository.py
clochette/application/repository/CalendarCacheRepository.py
clochette/application/repository/CalendarRepository.py
clochette/application/repository/SnoozeRepository.py
clochette/application/repository/__init__.py
clochette/application/service/EventModel.py
clochette/application/service/SnoozeModel.py
clochette/application/service/__init__.py
clochette/application/service/configurartion/SourceConfigurationMapperStrategy.py
clochette/application/service/configurartion/__init__.py
clochette/application/service/delta/__init__.py
clochette/application/service/download/CalendarDownloaderStrategyService.py
clochette/application/service/download/DownloaderService.py
clochette/application/service/download/__init__.py
clochette/application/service/ical/ICalendarService.py
clochette/application/service/ical/RRuleParserService.py
clochette/application/service/ical/TriggerIteratorFactory.py
clochette/application/service/ical/__init__.py
clochette/application/service/ical/dto/EventDTO.py
clochette/application/service/ical/dto/ExclusionDTO.py
clochette/application/service/ical/dto/__init__.py
clochette/application/service/provider/ProviderRegisterService.py
clochette/application/service/provider/__init__.py
clochette/application/service/provider/dto/IAuthenticationComponent.py
clochette/application/service/provider/dto/IDownloadCalendar.py
clochette/application/service/provider/dto/IProviderConfigurationMapper.py
clochette/application/service/provider/dto/ProviderDTO.py
clochette/application/service/provider/dto/ProviderType.py
clochette/application/service/provider/dto/__init__.py
clochette/application/store/CalendarConfigurationStore.py
clochette-0.2.4.dist-info/licenses/LICENSE
clochette-0.2.4.dist-info/WHEEL
clochette-0.2.4.dist-info/entry_points.txt
clochette-0.2.4.dist-info/METADATA
clochette-0.2.4.dist-info/RECORD
