Metadata-Version: 2.4
Name: Clochette
Version: 0.2.4
Summary: Clochette (from the French word meaning little bell) is a desktop reminder application written in Python and QT.
License-Expression: MIT
License-File: LICENSE
Requires-Dist: icalendar~=6.1.0
Requires-Dist: python-dateutil~=2.9.0.post0
Requires-Dist: requests~=2.32.5
Requires-Dist: requests-oauthlib~=2.0.0
Requires-Dist: pyside6~=6.10.1
Requires-Dist: pyside6-addons~=6.10.1
Requires-Dist: reactivex~=4.1.0
Requires-Dist: platformdirs~=4.5.1
Requires-Dist: isodate~=0.7.2
Requires-Dist: humanize~=4.15.0
Requires-Dist: babel~=2.17.0
Requires-Dist: keyring~=25.7.0
Requires-Dist: peewee~=3.19.0
Requires-Python: >=3.13
Project-URL: Homepage, https://gitlab.com/sketyl/clochette
Project-URL: Issues, https://gitlab.com/sketyl/clochette/-/issues
